log2tg_ng/__init__.py
log2tg_ng/formatters.py
log2tg_ng/handlers.py
logging2telegram_ng-1.1.0.dist-info/LICENSE
logging2telegram_ng-1.1.0.dist-info/METADATA
logging2telegram_ng-1.1.0.dist-info/WHEEL
logging2telegram_ng-1.1.0.dist-info/top_level.txt
logging2telegram_ng-1.1.0.dist-info/RECORD
