Metadata-Version: 2.1
Name: logging2telegram-ng
Version: 1.1.0
Summary: Telegram logging handler (next generation)
Home-page: https://github.com/jmfernandez/loging2telegram-ng
Author: jmfernandez
License: Apache License, Version 2.0, see LICENSE file
Platform: UNKNOWN
Classifier: License :: OSI Approved :: Apache Software License
Classifier: Operating System :: OS Independent
Classifier: Environment :: Console
Classifier: Development Status :: 3 - Alpha
Classifier: Programming Language :: Python
Classifier: Programming Language :: Python :: 3.7
Classifier: Programming Language :: Python :: Implementation :: PyPy
License-File: LICENSE
Requires-Dist: pyTelegramBotAPI (>=4.3.1)
